ffmpeg_python_utils/__init__.py
ffmpeg_python_utils/config.py
ffmpeg_python_utils/inc.py
ffmpeg_python_utils/main.py
ffmpeg_python_utils/other.py
ffmpeg_python_utils-0.0.1.dist-info/LICENSE
ffmpeg_python_utils-0.0.1.dist-info/METADATA
ffmpeg_python_utils-0.0.1.dist-info/WHEEL
ffmpeg_python_utils-0.0.1.dist-info/top_level.txt
ffmpeg_python_utils-0.0.1.dist-info/RECORD
