Metadata-Version: 2.1
Name: ffmpeg-python-utils
Version: 0.0.1
Summary: Python scripts constructing ffmpeg commands and running them by subprocess.
Home-page: https://github.com/LionelCrowl/ffmpeg-python-utils
Download-URL: https://github.com/LionelCrowl/ffmpeg-python-utils/archive/v0.0.1.zip
Author: LionelCrowl
Author-email: mr.lihenko@yandex.ru
License: MIT License, see LICENSE file
Classifier: Programming Language :: Python :: 3.10
Classifier: License :: OSI Approved :: MIT License
Classifier: Operating System :: OS Independent
License-File: LICENSE
Requires-Dist: numpy
Requires-Dist: librosa
Requires-Dist: matplotlib
Requires-Dist: pydub
Requires-Dist: scipy
